imandrax_codegen/__main__.py
imandrax_codegen/art_parse.exe
imandrax_codegen/art_parse.py
imandrax_codegen/ast_deserialize.py
imandrax_codegen/ast_types.py
imandrax_codegen/output.py
imandrax_codegen/test_gen.py
imandrax_codegen/unparse.py
imandrax_codegen/code_of_ast/__init__.py
imandrax_codegen/code_of_ast/__main__.py
imandrax_codegen-18.1.4.dist-info/METADATA
imandrax_codegen-18.1.4.dist-info/WHEEL
imandrax_codegen-18.1.4.dist-info/entry_points.txt
imandrax_codegen-18.1.4.dist-info/top_level.txt
imandrax_codegen-18.1.4.dist-info/RECORD
