Metadata-Version: 2.4
Name: imandrax-codegen
Version: 18.1.4
Summary: Code generator for ImandraX artifact
Author-email: hongyu <hongyu@imandra.ai>
Requires-Python: >=3.12
Requires-Dist: devtools>=0.12.2
Requires-Dist: dotenv>=0.9.9
Requires-Dist: imandrax-api-models>=18.0.0
Requires-Dist: imandrax-api[async]>=0.18.0.1
Requires-Dist: iml-query>=0.3.4
Requires-Dist: pydantic>=2.12.3
Requires-Dist: pyyaml>=6.0.3
Requires-Dist: rich>=14.2.0
Requires-Dist: ruff>=0.14.3
Requires-Dist: typer>=0.21.0
